[{"timestamp":"2025-11-09T00:28:48.497Z","count":0,"uniques":0},{"timestamp":"2025-11-10T00:28:48.497Z","count":0,"uniques":0},{"timestamp":"2025-11-11T00:28:48.497Z","count":0,"uniques":0},{"timestamp":"2025-11-12T00:30:14.496Z","count":0,"uniques":0},{"timestamp":"2025-11-13T00:30:14.496Z","count":0,"uniques":0},{"timestamp":"2025-11-14T00:30:14.496Z","count":0,"uniques":0},{"timestamp":"2025-11-15T00:30:14.496Z","count":0,"uniques":0},{"timestamp":"2025-11-16T00:30:14.496Z","count":0,"uniques":0}]
