[{"timestamp":"2025-01-14T00:25:56.006Z","count":0,"uniques":0},{"timestamp":"2025-01-15T00:25:56.006Z","count":0,"uniques":0},{"timestamp":"2025-01-16T00:25:56.006Z","count":0,"uniques":0},{"timestamp":"2025-01-17T00:25:39.785Z","count":0,"uniques":0},{"timestamp":"2025-01-18T00:25:39.785Z","count":0,"uniques":0},{"timestamp":"2025-01-19T00:25:39.785Z","count":0,"uniques":0},{"timestamp":"2025-01-20T00:25:39.785Z","count":0,"uniques":0},{"timestamp":"2025-01-21T00:25:39.785Z","count":0,"uniques":0}]
