[{"timestamp":"2023-06-01T22:25:51.896Z","count":0,"uniques":0},{"timestamp":"2023-07-01T00:23:26.564Z","count":28,"uniques":2},{"timestamp":"2023-08-01T00:25:24.868Z","count":1,"uniques":1},{"timestamp":"2023-09-01T00:19:38.839Z","count":0,"uniques":0},{"timestamp":"2023-10-01T00:20:03.563Z","count":0,"uniques":0},{"timestamp":"2023-11-01T00:20:16.468Z","count":0,"uniques":0},{"timestamp":"2023-12-01T00:20:50.421Z","count":0,"uniques":0},{"timestamp":"2024-01-01T00:20:35.633Z","count":0,"uniques":0},{"timestamp":"2024-02-01T00:19:56.244Z","count":0,"uniques":0},{"timestamp":"2024-03-01T00:20:48.213Z","count":0,"uniques":0},{"timestamp":"2024-04-01T00:19:51.224Z","count":0,"uniques":0},{"timestamp":"2024-05-01T00:21:17.182Z","count":0,"uniques":0}]
